lrcup/__init__.py
lrcup/__main__.py
lrcup/challenge.py
lrcup/controller.py
lrcup/audio/__init__.py
lrcup-0.10.2.dist-info/METADATA
lrcup-0.10.2.dist-info/WHEEL
lrcup-0.10.2.dist-info/entry_points.txt
lrcup-0.10.2.dist-info/licenses/LICENSE.txt
lrcup-0.10.2.dist-info/RECORD
