Metadata-Version: 2.4
Name: lrcup
Version: 0.10.2
Summary: Python module and CLI for the LRCLIB API
Project-URL: Homepage, https://github.com/iiPythonx/lrcup
Project-URL: Issues, https://github.com/iiPythonx/lrcup/issues
Author-email: iiPython <ben@iipython.dev>
License-Expression: MIT
License-File: LICENSE.txt
Classifier: Operating System :: OS Independent
Classifier: Programming Language :: Python :: 3
Requires-Python: >=3.10
Requires-Dist: click>=8.1.7
Requires-Dist: mutagen>=1.47.0
Requires-Dist: pydantic>=2.9.2
Requires-Dist: requests>=2.32.3
